zarnegar_converter
