Metadata-Version: 1.1
Name: zarnegar-converter
Version: 0.1.3
Summary: Converter for Zarnegar Encoding and File Format to Unicode Text Files
Home-page: https://github.com/behnam/python-zarnegar-converter
Author: Behnam Esfahbod
Author-email: behnam@zwnj.org
License: GNU General Public License, Version 3
Platform: UNKNOWN
Classifier: Development Status :: 4 - Beta
Classifier: Environment :: Console
Classifier: License :: OSI Approved :: GNU General Public License (GPL)
Classifier: Natural Language :: Persian
Classifier: Topic :: Software Development :: Internationalization
Classifier: Topic :: Text Editors
